kipu_client-0.0.3.dist-info/METADATA
kipu_client-0.0.3.dist-info/WHEEL
kipu_client/__init__.py
kipu_client/datascience/__init__.py
kipu_client/datascience/helpers.py
kipu_client/finance/__init__.py
kipu_client/finance/helpers.py
kipu_client/main.py
kipu_client/visualizations/__init__.py
kipu_client/visualizations/plots.py
kipu_client-0.0.3.dist-info/RECORD
