Metadata-Version: 2.1
Name: kipu-client
Version: 0.0.3
Summary: Python client for Kipu platform
Keywords: kipu python dcqo
Author-Email: Kipu Quantum GmbH <info@kipu-quantum.com>
License: MIT
Project-URL: Homepage, https://kipu-quantum.com
Project-URL: Documentation, http://docs.kipustack.com/
Project-URL: Registry, https://app.kipustack.com/
Requires-Python: <3.12,>=3.9
Requires-Dist: fastapi<1.0.0,>=0.95.0
Requires-Dist: requests<3.0.0,>=2.28.2
Requires-Dist: pandas<2.0.0,>=1.5.3
Requires-Dist: dimod<1.0.0,>=0.12.4
Requires-Dist: pyqubo<2.0.0,>=1.4.0
Requires-Dist: matplotlib>=3.8.2
